evina/__init__.py
evina/alipan.py
evina/config.py
evina/douyin.py
evina/douyu.py
evina/evina.py
evina/replacement.py
evina/ssh.py
evina-1.0.8.dist-info/LICENSE
evina-1.0.8.dist-info/METADATA
evina-1.0.8.dist-info/WHEEL
evina-1.0.8.dist-info/entry_points.txt
evina-1.0.8.dist-info/top_level.txt
evina-1.0.8.dist-info/RECORD
